midas/__init__.py
midas/estimator.py
midas/model_assessment.py
midas/setup.py
midas/core/__init__.py
midas/core/dmi.py
midas/utils/__init__.py
midas/utils/analytical_values.py
midas/utils/estimated_values.py
midas/utils/parameters_estimation.py
midas/utils/sample_generation.py
midas/utils/utilities.py
midasML-0.1.0.dist-info/DESCRIPTION.rst
midasML-0.1.0.dist-info/METADATA
midasML-0.1.0.dist-info/RECORD
midasML-0.1.0.dist-info/WHEEL
midasML-0.1.0.dist-info/metadata.json
midasML-0.1.0.dist-info/top_level.txt
