Metadata-Version: 2.0
Name: midasML
Version: 0.1.0
Summary: Multi Information estimator for Differential Co-regulation Analysis
Home-page: https://github.com/SheffieldML/midas
Author: Federico Tomasi
Author-email: federico.tomasi@dibris.unige.it
License: FreeBSD
Download-URL: https://github.com/SheffieldML/midas/tarball/0.1.0
Platform: UNKNOWN
Classifier: Development Status :: 4 - Beta
Classifier: Environment :: Console
Classifier: Intended Audience :: Science/Research
Classifier: Intended Audience :: Developers
Classifier: Programming Language :: Python
Classifier: License :: OSI Approved :: BSD License
Classifier: Topic :: Software Development
Classifier: Topic :: Scientific/Engineering :: Bio-Informatics
Classifier: Operating System :: POSIX
Classifier: Operating System :: Unix
Classifier: Operating System :: MacOS
Requires-Dist: numpy (>=1.10.1)
Requires-Dist: scipy (>=0.16.1)
Requires-Dist: scikit-learn (>=0.18)
